LICENSE
MANIFEST.in
README.md
pyproject.toml
setup.py
evenlyspacedstreamlines/__init__.py
evenlyspacedstreamlines/algebra.cpp
evenlyspacedstreamlines/algebra.h
evenlyspacedstreamlines/curvature.cpp
evenlyspacedstreamlines/curvature.h
evenlyspacedstreamlines/disjointintervals.cpp
evenlyspacedstreamlines/disjointintervals.h
evenlyspacedstreamlines/engine.cpp
evenlyspacedstreamlines/engine.h
evenlyspacedstreamlines/geometry.cpp
evenlyspacedstreamlines/geometry.h
evenlyspacedstreamlines/maxsubinterval.cpp
evenlyspacedstreamlines/quadraticforms.cpp
evenlyspacedstreamlines/quadraticforms.h
evenlyspacedstreamlines/runengine.cpp
evenlyspacedstreamlines/runengine.pyx
evenlyspacedstreamlines/segmentdeque.cpp
evenlyspacedstreamlines/segmentdeque.h
evenlyspacedstreamlines/segmentsearch.cpp
evenlyspacedstreamlines/segmentsearch.h
evenlyspacedstreamlines/streamlinecontainer.cpp
evenlyspacedstreamlines/streamlinecontainer.h
evenlyspacedstreamlines/streamlinetracer.cpp
evenlyspacedstreamlines/streamlinetracer.h
evenlyspacedstreamlines/timing.h
evenlyspacedstreamlines/triangle.cpp
evenlyspacedstreamlines/triangle.h
evenlyspacedstreamlines/triangularmesh.cpp
evenlyspacedstreamlines/triangularmesh.h
evenlyspacedstreamlines/wrapper.py
evenlyspacedstreamlines.egg-info/PKG-INFO
evenlyspacedstreamlines.egg-info/SOURCES.txt
evenlyspacedstreamlines.egg-info/dependency_links.txt
evenlyspacedstreamlines.egg-info/not-zip-safe
evenlyspacedstreamlines.egg-info/requires.txt
evenlyspacedstreamlines.egg-info/top_level.txt
evenlyspacedstreamlines/.vscode/settings.json