Metadata-Version: 2.1
Name: evenlyspacedstreamlines
Version: 0.1.0
Summary: Generate evenly-spaced streamlines from an orientation field on a triangulated 3D surface
Home-page: http://github.com/jacquemv/evenlyspacedstreamlines
Author: Vincent Jacquemet
Author-email: vincent.jacquemet@umontreal.ca
License: MIT
Keywords: vector,field,visualization,surface,streamline
License-File: LICENSE
